Metadata-Version: 2.1
Name: opencensus-ext-sqlalchemy
Version: 0.1.3
Summary: OpenCensus SQLAlchemy Integration
Home-page: https://github.com/census-instrumentation/opencensus-python/tree/master/contrib/opencensus-ext-sqlalchemy
Author: OpenCensus Authors
Author-email: census-developers@googlegroups.com
License: Apache-2.0
Platform: UNKNOWN
Classifier: Intended Audience :: Developers
Classifier: Development Status :: 3 - Alpha
Classifier: Intended Audience :: Developers
Classifier: License :: OSI Approved :: Apache Software License
Classifier: Programming Language :: Python
Classifier: Programming Language :: Python :: 2
Classifier: Programming Language :: Python :: 2.7
Classifier: Programming Language :: Python :: 3
Classifier: Programming Language :: Python :: 3.4
Classifier: Programming Language :: Python :: 3.5
Classifier: Programming Language :: Python :: 3.6
Classifier: Programming Language :: Python :: 3.7
Classifier: Programming Language :: Python :: 3.8
Classifier: Programming Language :: Python :: 3.9
Requires-Dist: opencensus (<1.0.0,>=0.8.0)
Requires-Dist: SQLAlchemy (<1.3.24,>=1.1.14)
